cwlbrowser/__init__.py
cwlbrowser/basic_similaritychecker.py
cwlbrowser/browser.py
cwlbrowser/input_output.py
cwlbrowser/similaritychecker.py
cwlbrowser/step.py
cwlbrowser/util.py
cwlbrowser/workflow.py
cwlbrowser-5.0.dist-info/DESCRIPTION.rst
cwlbrowser-5.0.dist-info/METADATA
cwlbrowser-5.0.dist-info/RECORD
cwlbrowser-5.0.dist-info/WHEEL
cwlbrowser-5.0.dist-info/metadata.json
cwlbrowser-5.0.dist-info/top_level.txt
