Metadata-Version: 2.0
Name: cwlbrowser
Version: 5.0
Summary: Python library that browses and analyses workflows in CWL
Home-page: https://gitlab.cs.man.ac.uk/mbaxasp7/cwlbrowser
Author: Sean Pertet
Author-email: sean.pertet@student.manchester.ac.uk
License: UNKNOWN
Platform: UNKNOWN
Classifier: Programming Language :: Python :: 3
Classifier: License :: OSI Approved :: MIT License
Classifier: Operating System :: OS Independent
Requires-Dist: IPython
Requires-Dist: cwlref-runner
Requires-Dist: pyyaml
Requires-Dist: requests
